MANIFEST.in
setup.py
tox.ini
mailboxer/__init__.py
mailboxer/__version__.py
mailboxer/mailboxer.py
mailboxer/query.py
mailboxer_python.egg-info/PKG-INFO
mailboxer_python.egg-info/SOURCES.txt
mailboxer_python.egg-info/dependency_links.txt
mailboxer_python.egg-info/namespace_packages.txt
mailboxer_python.egg-info/requires.txt
mailboxer_python.egg-info/top_level.txt
tests/__init__.py
tests/__init__.pyc
tests/conftest.py
tests/test_mailboxer.py