Metadata-Version: 1.1
Name: mailboxer-python
Version: 1.3.1
Summary: Client library for Mailboxer
Home-page: https://github.com/vmalloc/mailboxer-python
Author: Rotem Yaari
Author-email: vmalloc@gmail.com
License: BSD3
Platform: UNKNOWN
Classifier: Programming Language :: Python :: 2.6
Classifier: Programming Language :: Python :: 2.7
Classifier: Programming Language :: Python :: 3.3
